README.md
dnode.py
setup.py
dnode.egg-info/PKG-INFO
dnode.egg-info/SOURCES.txt
dnode.egg-info/dependency_links.txt
dnode.egg-info/requires.txt
dnode.egg-info/top_level.txt