Metadata-Version: 2.1
Name: dnode
Version: 0.2.6
Summary: read/write json as a object | 像读写对象属性一样读写 json
Home-page: https://github.com/taojy123/dnode
Author: tao.py
Author-email: taojy123@163.com
Maintainer: tao.py
Maintainer-email: taojy123@163.com
License: MIT License
Platform: all
Classifier: Programming Language :: Python
Classifier: Programming Language :: Python :: Implementation
Classifier: Programming Language :: Python :: 2
Classifier: Programming Language :: Python :: 3
Classifier: Topic :: Software Development :: Libraries
